hivemind/__init__.py
hivemind/averaging/__init__.py
hivemind/averaging/allreduce.py
hivemind/averaging/averager.py
hivemind/averaging/control.py
hivemind/averaging/group_info.py
hivemind/averaging/key_manager.py
hivemind/averaging/load_balancing.py
hivemind/averaging/matchmaking.py
hivemind/averaging/partition.py
hivemind/compression/__init__.py
hivemind/compression/adaptive.py
hivemind/compression/base.py
hivemind/compression/floating.py
hivemind/compression/quantization.py
hivemind/compression/serialization.py
hivemind/dht/__init__.py
hivemind/dht/crypto.py
hivemind/dht/dht.py
hivemind/dht/node.py
hivemind/dht/protocol.py
hivemind/dht/routing.py
hivemind/dht/schema.py
hivemind/dht/storage.py
hivemind/dht/traverse.py
hivemind/dht/validation.py
hivemind/hivemind_cli/__init__.py
hivemind/hivemind_cli/config.yml
hivemind/hivemind_cli/p2pd
hivemind/hivemind_cli/run_dht.py
hivemind/hivemind_cli/run_server.py
hivemind/moe/__init__.py
hivemind/moe/expert_uid.py
hivemind/moe/client/__init__.py
hivemind/moe/client/beam_search.py
hivemind/moe/client/expert.py
hivemind/moe/client/moe.py
hivemind/moe/client/remote_expert_worker.py
hivemind/moe/client/switch_moe.py
hivemind/moe/server/__init__.py
hivemind/moe/server/checkpoints.py
hivemind/moe/server/connection_handler.py
hivemind/moe/server/dht_handler.py
hivemind/moe/server/module_backend.py
hivemind/moe/server/runtime.py
hivemind/moe/server/server.py
hivemind/moe/server/task_pool.py
hivemind/moe/server/layers/__init__.py
hivemind/moe/server/layers/common.py
hivemind/moe/server/layers/custom_experts.py
hivemind/moe/server/layers/dropout.py
hivemind/moe/server/layers/lr_schedule.py
hivemind/moe/server/layers/optim.py
hivemind/optim/__init__.py
hivemind/optim/grad_averager.py
hivemind/optim/grad_scaler.py
hivemind/optim/optimizer.py
hivemind/optim/power_sgd_averager.py
hivemind/optim/progress_tracker.py
hivemind/optim/state_averager.py
hivemind/optim/training_averager.py
hivemind/p2p/__init__.py
hivemind/p2p/p2p_daemon.py
hivemind-1.1.11.dist-info/licenses/LICENSE
hivemind-1.1.11.dist-info/METADATA
hivemind-1.1.11.dist-info/WHEEL
hivemind-1.1.11.dist-info/entry_points.txt
hivemind-1.1.11.dist-info/top_level.txt
hivemind-1.1.11.dist-info/RECORD
